hydroanomaly/__init__.py
hydroanomaly/ml.py
hydroanomaly/sentinel_bands.py
hydroanomaly/usgs_turbidity.py
hydroanomaly/visualize.py
hydroanomaly-1.2.9.dist-info/METADATA
hydroanomaly-1.2.9.dist-info/WHEEL
hydroanomaly-1.2.9.dist-info/top_level.txt
hydroanomaly-1.2.9.dist-info/RECORD
