Metadata-Version: 2.4
Name: hydroanomaly
Version: 1.2.9
Summary: A Python package for hydro anomaly detection with simple USGS data retrieval
Author-email: Ehsan Kahrizi <ehsan.kahrizi@usu.edu>
Project-URL: Homepage, https://github.com/Ehsankahrizi/HydroAnomaly
Project-URL: Bug Reports, https://github.com/Ehsankahrizi/HydroAnomaly/issues
Project-URL: Source, https://github.com/Ehsankahrizi/HydroAnomaly
Keywords: python,package,hydrology,anomaly detection,remote sensing
Classifier: Programming Language :: Python :: 3
Classifier: License :: OSI Approved :: MIT License
Classifier: Operating System :: OS Independent
Requires-Python: >=3.6
Requires-Dist: pandas>=1.3.0
Requires-Dist: numpy>=1.20.0
Requires-Dist: requests>=2.25.1
Requires-Dist: matplotlib>=3.3.0
Requires-Dist: seaborn>=0.11.0
Requires-Dist: earthengine-api>=0.1.300
Requires-Dist: geemap>=0.20.0
Requires-Dist: tqdm>=4.60.0
Requires-Dist: scipy>=1.7.0
Requires-Dist: scikit-learn>=1.0.0
Provides-Extra: dev
Requires-Dist: pytest>=6.0; extra == "dev"
Requires-Dist: black>=21.0; extra == "dev"
Requires-Dist: flake8>=3.8; extra == "dev"
Requires-Dist: mypy>=0.800; extra == "dev"
